chemview/__init__.py
chemview/app.py
chemview/contrib.py
chemview/export.py
chemview/gg.py
chemview/install.py
chemview/layout.py
chemview/marchingcubes.py
chemview/render.py
chemview/scene.py
chemview/trajectory.py
chemview/utils.py
chemview/viewer.py
chemview/widget.py
chemview/static/ArcballControls.js
chemview/static/MarchingCubes.js
chemview/static/Stats.js
chemview/static/__init__.py
chemview/static/base64-arraybuffer.js
chemview/static/chemview.js
chemview/static/chemview_widget.js
chemview/static/config_test.js
chemview/static/context.js
chemview/static/context.standalone.css
chemview/static/filesaver.js
chemview/static/floatrange_widget.js
chemview/static/jquery-2.2.0.min.js
chemview/static/jquery-ui.min.css
chemview/static/jquery-ui.min.js
chemview/static/layout_widget.js
chemview/static/objexporter.js
chemview/static/scales.js
chemview/static/screenfull.min.js
chemview/static/surface.min.js
chemview/static/three.min.js
chemview/static/trajectory_controls_widget.js
chemview/static/components/__init__.py
chemview/static/components/config_test.js
chemview/static/components/jquery-fullscreen/__init__.py
chemview/static/components/jquery-fullscreen/jquery.fullscreen-min.js
chemview/static/components/jquery-fullscreen/jquery.fullscreen.js
chemview-0.6.dist-info/DESCRIPTION.rst
chemview-0.6.dist-info/METADATA
chemview-0.6.dist-info/RECORD
chemview-0.6.dist-info/WHEEL
chemview-0.6.dist-info/metadata.json
chemview-0.6.dist-info/top_level.txt
tests/__init__.py
tests/test_gg.py
tests/test_povray.py
tests/test_scene.py
