Metadata-Version: 2.0
Name: chemview
Version: 0.6
Summary: Interactive molecular viewer for IPython notebook
Home-page: https://github.com/gabrielelanaro/chemview
Author: Gabriele Lanaro
Author-email: gabriele.lanaro@gmail.com
License: UNKNOWN
Platform: UNKNOWN
Requires-Dist: matplotlib
Requires-Dist: notebook
Requires-Dist: numpy
Requires-Dist: vapory
